friendlyetl/__init__.py
friendlyetl/etl.py
friendlyetl-1.0.3.dist-info/LICENSE
friendlyetl-1.0.3.dist-info/METADATA
friendlyetl-1.0.3.dist-info/WHEEL
friendlyetl-1.0.3.dist-info/top_level.txt
friendlyetl-1.0.3.dist-info/RECORD
