Metadata-Version: 2.1
Name: friendlyetl
Version: 1.0.3
Summary: A simple and lightweight ETL package for data pipelines using Python, Pandas, PySpark, and Hadoop
Author: Divith Raju
Author-email: divithraju@gmail.com
Classifier: Programming Language :: Python :: 3
Classifier: License :: OSI Approved :: MIT License
Classifier: Operating System :: OS Independent
Classifier: Intended Audience :: Developers
Classifier: Topic :: Software Development :: Build Tools
Classifier: Topic :: Database :: Front-Ends
Requires-Python: >=3.6
License-File: LICENSE
Requires-Dist: pandas
Requires-Dist: pyspark
Requires-Dist: sqlalchemy
Requires-Dist: mysql-connector-python
